easyscraper/Classes.py
easyscraper/Images.py
easyscraper/Words.py
easyscraper/__init__.py
easyscraper-0.0.1.dist-info/LICENSE
easyscraper-0.0.1.dist-info/METADATA
easyscraper-0.0.1.dist-info/WHEEL
easyscraper-0.0.1.dist-info/top_level.txt
easyscraper-0.0.1.dist-info/RECORD
