Metadata-Version: 2.1
Name: easyscraper
Version: 0.0.1
Summary: scrape images relevant to your text passage
Home-page: https://github.com/yishairasowsky/easyscraper
Author: yishai rasowsky
Author-email: yishairasowsky@gmail.com
License: UNKNOWN
Platform: UNKNOWN
Classifier: Programming Language :: Python :: 3
Classifier: License :: OSI Approved :: MIT License
Classifier: Operating System :: OS Independent
Requires-Python: >=3.6
